thorlabs_xa/__init__.py
thorlabs_xa/tlmc_xa_native.dll
thorlabs_xa/implementations/__init__.py
thorlabs_xa/implementations/device_feature_groups/__init__.py
thorlabs_xa/implementations/device_feature_groups/kpc101_feature_group.py
thorlabs_xa/implementations/device_feature_groups/lnnx_feature_group.py
thorlabs_xa/implementations/device_feature_groups/lnnx_logical_channel_feature_group.py
thorlabs_xa/implementations/device_features/__init__.py
thorlabs_xa/implementations/device_features/adc_inputs_feature.py
thorlabs_xa/implementations/device_features/analog_monitor_configuration_params_feature.py
thorlabs_xa/implementations/device_features/aux_io_configuration_params_feature.py
thorlabs_xa/implementations/device_features/bow_index_feature.py
thorlabs_xa/implementations/device_features/button_params_feature.py
thorlabs_xa/implementations/device_features/calibration_feature.py
thorlabs_xa/implementations/device_features/connected_product_feature.py
thorlabs_xa/implementations/device_features/current_loop_params_feature.py
thorlabs_xa/implementations/device_features/dc_pid_params_feature.py
thorlabs_xa/implementations/device_features/digital_input_states_feature.py
thorlabs_xa/implementations/device_features/digital_output_states_feature.py
thorlabs_xa/implementations/device_features/disconnect_feature.py
thorlabs_xa/implementations/device_features/enable_state_feature.py
thorlabs_xa/implementations/device_features/encoder_counter_feature.py
thorlabs_xa/implementations/device_features/end_of_move_message_mode_feature.py
thorlabs_xa/implementations/device_features/firmware_version_info_feature.py
thorlabs_xa/implementations/device_features/general_move_params_feature.py
thorlabs_xa/implementations/device_features/hardware_info_feature.py
thorlabs_xa/implementations/device_features/home_feature.py
thorlabs_xa/implementations/device_features/home_params_feature.py
thorlabs_xa/implementations/device_features/identify_feature.py
thorlabs_xa-1.0.0.26692.dist-info/licenses/LICENSE
thorlabs_xa-1.0.0.26692.dist-info/METADATA
thorlabs_xa-1.0.0.26692.dist-info/WHEEL
thorlabs_xa-1.0.0.26692.dist-info/top_level.txt
thorlabs_xa-1.0.0.26692.dist-info/RECORD
