Metadata-Version: 2.4
Name: thorlabs_xa
Version: 1.0.0.26692
Summary: Python wrapper of the Thorlabs  XA SDK
Author: Thorlabs
Author-email: techsupport@thorlabs.com
License: BSD-3-Clause
Classifier: Programming Language :: Python :: 3
Classifier: Operating System :: Microsoft :: Windows
Classifier: Operating System :: POSIX :: Linux
Requires-Python: >=3.10, <4
License-File: LICENSE
Dynamic: author
Dynamic: author-email
Dynamic: classifier
Dynamic: description
Dynamic: description-content-type
Dynamic: license
Dynamic: license-file
Dynamic: requires-python
Dynamic: summary
